sqldisplay/__init__.py
sqldisplay/sqldisplay.py
sqldisplay-1.0.4.dist-info/METADATA
sqldisplay-1.0.4.dist-info/WHEEL
sqldisplay-1.0.4.dist-info/licenses/LICENSE
sqldisplay-1.0.4.dist-info/RECORD
