Metadata-Version: 2.1
Name: sqldisplay
Version: 1.0.4
Summary: A simple package to make displaying SQL queries much easier
Project-URL: Homepage, https://github.com/Guinea1/sqldisplay
Author-email: Bobby D <bobbydapps@gmail.com>
License-File: LICENSE
Classifier: License :: OSI Approved :: MIT License
Classifier: Operating System :: OS Independent
Classifier: Programming Language :: Python :: 3
Requires-Python: >=3.7
